CHANGES.md
MANIFEST.in
README.md
setup.cfg
setup.py
donkey/__init__.py
donkey/compat.py
donkey/job.py
donkey/worker.py
donkey.egg-info/PKG-INFO
donkey.egg-info/SOURCES.txt
donkey.egg-info/dependency_links.txt
donkey.egg-info/pbr.json
donkey.egg-info/requires.txt
donkey.egg-info/top_level.txt