Metadata-Version: 1.1
Name: donkey
Version: 0.0.2
Summary: A simple cron-like library for executing scheduled jobs.
Home-page: https://github.com/bcho/donkey
Author: hbc
Author-email: bcxxxxxx@gmail.com
License: MIT
Platform: UNKNOWN
Classifier: Development Status :: 4 - Beta
Classifier: Operating System :: POSIX :: Linux
Classifier: Programming Language :: Python :: 3
Classifier: Programming Language :: Python :: 2
Classifier: Topic :: Software Development :: Libraries :: Python Modules
Classifier: Intended Audience :: Developers
Classifier: License :: OSI Approved :: MIT License
